leocli/__init__.py
leocli/cache.py
leocli/conf.py
leocli/consts.py
leocli/leo.py
leocli-3.4.4.dist-info/COPYING
leocli-3.4.4.dist-info/METADATA
leocli-3.4.4.dist-info/WHEEL
leocli-3.4.4.dist-info/entry_points.txt
leocli-3.4.4.dist-info/RECORD
